slackette/__init__.py
slackette/blocks.py
slackette/interactions.py
slackette/py.typed
slackette/security.py
slackette/types.py
slackette/webhook.py
slackette-0.2.5.dist-info/WHEEL
slackette-0.2.5.dist-info/METADATA
slackette-0.2.5.dist-info/RECORD
